cli/__init__.py
cli/_cli.py
main/__init__.py
icnc-1.0.1.dist-info/METADATA
icnc-1.0.1.dist-info/WHEEL
icnc-1.0.1.dist-info/entry_points.txt
icnc-1.0.1.dist-info/top_level.txt
icnc-1.0.1.dist-info/RECORD
