Metadata-Version: 2.1
Name: icnc
Version: 1.0.1
Classifier: Programming Language :: Python :: 3
Classifier: License :: OSI Approved :: MIT License
Classifier: Operating System :: OS Independent
Requires-Python: >=3.6
Requires-Dist: python-dotenv
Requires-Dist: openai ==0.12.6
